devicebay/__init__.py
devicebay/base.py
devicebay/config.py
devicebay/db/conn.py
devicebay/db/models.py
devicebay/devices/browser.py
devicebay/devices/filesystem.py
devicebay/devices/gh.py
devicebay/models.py
devicebay/types.py
devicebay-0.1.28.dist-info/LICENSE
devicebay-0.1.28.dist-info/METADATA
devicebay-0.1.28.dist-info/WHEEL
devicebay-0.1.28.dist-info/RECORD
