Metadata-Version: 2.1
Name: devicebay
Version: 0.1.28
Summary: Devices for AI agents
License: MIT
Author: Patrick Barker
Author-email: patrickbarkerco@gmail.com
Requires-Python: >=3.10,<4.0
Classifier: License :: OSI Approved :: MIT License
Classifier: Programming Language :: Python :: 3
Classifier: Programming Language :: Python :: 3.10
Classifier: Programming Language :: Python :: 3.11
Classifier: Programming Language :: Python :: 3.12
Provides-Extra: browser
Provides-Extra: github
Requires-Dist: playwright[browser] (>=1.43.0,<2.0.0) ; extra == "browser"
Requires-Dist: pygithub[github] (>=2.3.0,<3.0.0) ; extra == "github"
Requires-Dist: sqlalchemy (>=2.0.29,<3.0.0)
Requires-Dist: toolfuse (>=0.1.25,<0.2.0)
